LICENSE
MANIFEST.in
README.md
pyproject.toml
setup.py
philtorch/VERSION.txt
philtorch/__init__.py
philtorch/_version.py
philtorch/core.py
philtorch/mat.py
philtorch/poly.py
philtorch/utils.py
philtorch.egg-info/PKG-INFO
philtorch.egg-info/SOURCES.txt
philtorch.egg-info/dependency_links.txt
philtorch.egg-info/not-zip-safe
philtorch.egg-info/requires.txt
philtorch.egg-info/top_level.txt
philtorch/csrc/host_lti_recur.cpp
philtorch/csrc/host_lti_recurN.cpp
philtorch/csrc/host_recur2.cpp
philtorch/csrc/host_recurN.cpp
philtorch/csrc/lti_recur.cu
philtorch/csrc/lti_recur2.cu
philtorch/csrc/recur2.cu
philtorch/csrc/recur2.cuh
philtorch/lpv/__init__.py
philtorch/lpv/filtering.py
philtorch/lpv/recur.py
philtorch/lpv/ssm.py
philtorch/lpv/utils.py
philtorch/lti/__init__.py
philtorch/lti/filtering.py
philtorch/lti/interp.py
philtorch/lti/recur.py
philtorch/lti/ssm.py
philtorch/prototype/poly.py
philtorch/prototype/signal.py