Metadata-Version: 2.4
Name: philtorch
Version: 0.2
Summary: A PyTorch library for time-varying IIR filters.
Author-email: Chin-Yun Yu <chin-yun.yu@qmul.ac.uk>
Maintainer-email: Chin-Yun Yu <chin-yun.yu@qmul.ac.uk>
License: MIT
Classifier: Development Status :: 3 - Alpha
Classifier: Intended Audience :: Developers
Classifier: Programming Language :: Python :: 3
Classifier: Programming Language :: Python :: 3.10
Classifier: Programming Language :: Python :: 3.11
Classifier: Programming Language :: Python :: 3.12
Requires-Python: >=3.10
License-File: LICENSE
Requires-Dist: torch>=2.0.0
Requires-Dist: torchlpc>=0.7.2
Provides-Extra: dev
Requires-Dist: pytest>=6.0; extra == "dev"
Requires-Dist: scipy; extra == "dev"
Requires-Dist: numpy; extra == "dev"
Requires-Dist: pytest-cov; extra == "dev"
Dynamic: license-file
